swh/deposit/__init__.py
swh/deposit/apps.py
swh/deposit/auth.py
swh/deposit/client.py
swh/deposit/config.py
swh/deposit/errors.py
swh/deposit/exception.py
swh/deposit/gunicorn_config.py
swh/deposit/manage.py
swh/deposit/models.py
swh/deposit/parsers.py
swh/deposit/py.typed
swh/deposit/urls.py
swh/deposit/utils.py
swh/deposit/api/__init__.py
swh/deposit/api/collection.py
swh/deposit/api/common.py
swh/deposit/api/content.py
swh/deposit/api/converters.py
swh/deposit/api/edit.py
swh/deposit/api/edit_media.py
swh/deposit/api/service_document.py
swh/deposit/api/state.py
swh/deposit/api/sword_edit.py
swh/deposit/api/urls.py
swh/deposit/api/utils.py
swh/deposit/api/private/__init__.py
swh/deposit/api/private/deposit_list.py
swh/deposit/api/private/deposit_read.py
swh/deposit/api/private/deposit_releases.py
swh/deposit/api/private/deposit_update_status.py
swh/deposit/api/private/deposit_upload_urls.py
swh/deposit/api/private/urls.py
swh/deposit/cli/__init__.py
swh/deposit/cli/admin.py
swh/deposit/cli/client.py
swh/deposit/fixtures/__init__.py
swh/deposit/fixtures/deposit_data.yaml
swh/deposit/loader/__init__.py
swh/deposit/loader/checker.py
swh/deposit/loader/checks.py
swh/deposit/loader/tasks.py
swh/deposit/migrations/0001_initial.py
swh/deposit/migrations/0002_depositrequest_archive.py
swh/deposit/migrations/0003_temporaryarchive.py
swh/deposit/migrations/0004_delete_temporaryarchive.py
swh/deposit/migrations/0005_auto_20171019_1436.py
swh/deposit/migrations/0006_depositclient_url.py
swh/deposit/migrations/0007_auto_20171129_1609.py
swh/deposit/migrations/0008_auto_20171130_1513.py
swh/deposit/migrations/0009_deposit_parent.py
swh/deposit/migrations/0010_auto_20180110_0953.py
swh/deposit/migrations/0011_auto_20180115_1510.py
swh/deposit/migrations/0012_deposit_status_detail.py
swh/deposit/migrations/0013_depositrequest_raw_metadata.py
swh/deposit/migrations/0014_auto_20180720_1221.py
swh/deposit/migrations/0015_depositrequest_typemigration.py
swh_deposit-3.0.0.dist-info/licenses/AUTHORS
swh_deposit-3.0.0.dist-info/licenses/LICENSE
swh_deposit-3.0.0.dist-info/METADATA
swh_deposit-3.0.0.dist-info/WHEEL
swh_deposit-3.0.0.dist-info/entry_points.txt
swh_deposit-3.0.0.dist-info/top_level.txt
swh_deposit-3.0.0.dist-info/RECORD
