Metadata-Version: 2.4
Name: swh.deposit
Version: 3.0.0
Summary: Software Heritage deposit server
Author-email: Software Heritage developers <swh-devel@inria.fr>
Project-URL: Homepage, https://gitlab.softwareheritage.org/swh/devel/swh-deposit
Project-URL: Bug Reports, https://gitlab.softwareheritage.org/swh/devel/swh-deposit/-/issues
Project-URL: Funding, https://www.softwareheritage.org/donate
Project-URL: Documentation, https://docs.softwareheritage.org/devel/swh-deposit/
Project-URL: Source, https://gitlab.softwareheritage.org/swh/devel/swh-deposit.git
Classifier: Programming Language :: Python :: 3
Classifier: Intended Audience :: Developers
Classifier: License :: OSI Approved :: GNU General Public License v3 (GPLv3)
Classifier: Operating System :: OS Independent
Classifier: Development Status :: 5 - Production/Stable
Requires-Python: >=3.7
License-File: LICENSE
License-File: AUTHORS
Requires-Dist: click
Requires-Dist: iso8601
Requires-Dist: requests
Requires-Dist: sentry-sdk
Requires-Dist: xmlschema
Requires-Dist: swh.core[http]>=4.0.0
Requires-Dist: swh.model>=6.13.0
Provides-Extra: server
Requires-Dist: django; extra == "server"
Requires-Dist: djangorestframework; extra == "server"
Requires-Dist: psycopg; extra == "server"
Requires-Dist: setuptools; extra == "server"
Requires-Dist: pymemcache; extra == "server"
Requires-Dist: swh.core[http]>=4.0.0; extra == "server"
Requires-Dist: swh.loader.core>=0.0.71; extra == "server"
Requires-Dist: swh.scheduler>=3.0.0; extra == "server"
Requires-Dist: swh.model>=6.13.0; extra == "server"
Requires-Dist: swh.auth[django]>=0.5.3; extra == "server"
Requires-Dist: swh.storage>=3.0.0; extra == "server"
Provides-Extra: azure
Requires-Dist: django-storages[azure]; extra == "azure"
Provides-Extra: testing
Requires-Dist: pytest; extra == "testing"
Requires-Dist: pytest-django; extra == "testing"
Requires-Dist: pytest-mock; extra == "testing"
Requires-Dist: swh.scheduler[testing]>=3.0.0; extra == "testing"
Requires-Dist: swh.loader.core[testing]>=4.0.0; extra == "testing"
Requires-Dist: pytest-postgresql>=5; extra == "testing"
Requires-Dist: requests_mock; extra == "testing"
Requires-Dist: django-stubs; extra == "testing"
Requires-Dist: djangorestframework-stubs>=1.4; extra == "testing"
Requires-Dist: django-test-migrations; extra == "testing"
Requires-Dist: celery-types; extra == "testing"
Requires-Dist: types-requests; extra == "testing"
Requires-Dist: types-pyyaml; extra == "testing"
Requires-Dist: django; extra == "testing"
Requires-Dist: djangorestframework; extra == "testing"
Requires-Dist: psycopg; extra == "testing"
Requires-Dist: setuptools; extra == "testing"
Requires-Dist: pymemcache; extra == "testing"
Requires-Dist: swh.core[http]>=4.0.0; extra == "testing"
Requires-Dist: swh.loader.core>=0.0.71; extra == "testing"
Requires-Dist: swh.scheduler>=3.0.0; extra == "testing"
Requires-Dist: swh.model>=6.13.0; extra == "testing"
Requires-Dist: swh.auth[django]>=0.5.3; extra == "testing"
Requires-Dist: swh.storage>=3.0.0; extra == "testing"
Requires-Dist: django-storages[azure]; extra == "testing"
Dynamic: license-file
